bloom/__init__.py
bloom/bloom.py
jmespath/__init__.py
jmespath/ast.py
jmespath/compat.py
jmespath/exceptions.py
jmespath/functions.py
jmespath/lexer.py
jmespath/parser.py
jmespath/visitor.py
semanticstore/__init__.py
semanticstore/closure.py
semanticstore/cursor.py
semanticstore/kv.py
semanticstore/utils.py
tests/__init__.py
tests/kvdb_core.py
semantic_store-0.0.15.dist-info/METADATA
semantic_store-0.0.15.dist-info/WHEEL
semantic_store-0.0.15.dist-info/top_level.txt
semantic_store-0.0.15.dist-info/RECORD
