Metadata-Version: 2.1
Name: semantic-store
Version: 0.0.15
Summary: An embedded vector database for semantic data storage and retrieval
Author: Pragnesh Barik
Keywords: embedded database,vector,database,semantic,search
Requires-Dist: faiss-cpu ==1.7.4
Requires-Dist: bitarray ==2.8.1
Requires-Dist: mmh3 ==4.0.1
Requires-Dist: numpy ==1.26.0
